pv_ts_sandbox/__init__.py
pv_ts_sandbox/analysis.py
pv_ts_sandbox/dataformatter.py
pv_ts_sandbox/metadata_sample.csv
pv_ts_sandbox/metadata_template.csv
pv_ts_sandbox/metadata_template_compressed.csv
pv_ts_sandbox/preprocess.py
pv_ts_sandbox/pv-proj-metadata.csv
pv_ts_sandbox/requirements.txt
pv_ts_sandbox/visualize.py
pv_ts_sandbox-0.0.1.dist-info/LICENSE
pv_ts_sandbox-0.0.1.dist-info/METADATA
pv_ts_sandbox-0.0.1.dist-info/WHEEL
pv_ts_sandbox-0.0.1.dist-info/top_level.txt
pv_ts_sandbox-0.0.1.dist-info/RECORD
