Metadata-Version: 2.1
Name: pv-ts-sandbox
Version: 0.0.1
Summary: Package designed for Analysis & Visualization of Photovoltaic Datasets
Author: Fall 2023 Senior Design Photovoltaics Team
Classifier: Programming Language :: Python :: 3
Classifier: License :: OSI Approved :: MIT License
Classifier: Operating System :: OS Independent
Requires-Python: >=3.7
License-File: LICENSE
